ha_vector/__init__.py
ha_vector/animation.py
ha_vector/annotate.py
ha_vector/audio.py
ha_vector/behavior.py
ha_vector/camera.py
ha_vector/color.py
ha_vector/connection.py
ha_vector/events.py
ha_vector/exceptions.py
ha_vector/faces.py
ha_vector/lights.py
ha_vector/mdns.py
ha_vector/motors.py
ha_vector/nav_map.py
ha_vector/objects.py
ha_vector/photos.py
ha_vector/proximity.py
ha_vector/robot.py
ha_vector/screen.py
ha_vector/status.py
ha_vector/touch.py
ha_vector/user_intent.py
ha_vector/util.py
ha_vector/version.py
ha_vector/viewer.py
ha_vector/vision.py
ha_vector/world.py
ha_vector/camera_viewer/__init__.py
ha_vector/opengl/__init__.py
ha_vector/opengl/opengl.py
ha_vector/opengl/opengl_vector.py
ha_vector/opengl/opengl_viewer.py
ha_vector-0.0.1.dist-info/LICENSE
ha_vector-0.0.1.dist-info/METADATA
ha_vector-0.0.1.dist-info/WHEEL
ha_vector-0.0.1.dist-info/top_level.txt
ha_vector-0.0.1.dist-info/RECORD
