Metadata-Version: 2.1
Name: ha-vector
Version: 0.0.1
Summary: Home Assistant Vector SDK implementation
Home-page: https://github.com/mtrab/ha_vector
Author: Malene Trab
Author-email: malene@trab.dk
License: MIT
Project-URL: Bug Tracker, https://github.com/mtrab/ha_vector/issues
Platform: UNKNOWN
Requires-Dist: Pillow (>=3.3)
Requires-Dist: aiogrpc (>=1.4)
Requires-Dist: cryptography (>=36.0.2)
Requires-Dist: flask (>=2.1.0)
Requires-Dist: googleapis-common-protos (>=1.56.0)
Requires-Dist: grpc-tools (>=0.0.1)
Requires-Dist: grpcio-tools (>=1.47.0)
Requires-Dist: numpy (>=1.11)
Requires-Dist: requests (>=2.0.0)
